{
    "version": "0.6.43",
    "architecture": {
        "32bit": {
            "url": "https://github.com/meshery/meshery/releases/download/v0.6.43/mesheryctl_0.6.43_Windows_i386.zip",
            "bin": [
                "mesheryctl.exe"
            ],
            "hash": "4cf70a6695cc9d329801a88806bfea655576d8008563d90278aa4be5fd546250"
        },
        "64bit": {
            "url": "https://github.com/meshery/meshery/releases/download/v0.6.43/mesheryctl_0.6.43_Windows_x86_64.zip",
            "bin": [
                "mesheryctl.exe"
            ],
            "hash": "d981c1e22fe4f07975e7014bd6d2e50f7655cfe603d4e91302e0aa1f823c18a4"
        }
    },
    "homepage": "https://layer5.io/meshery",
    "license": "Apache 2.0",
    "description": "The Cloud Native Management Plane."
}