{
    "version": "0.6.0-rc.6fe",
    "architecture": {
        "32bit": {
            "url": "https://github.com/meshery/meshery/releases/download/v0.6.0-rc.6fe/mesheryctl_0.6.0-rc.6fe_Windows_i386.zip",
            "bin": [
                "mesheryctl.exe"
            ],
            "hash": "aae2e27c3cd1d226a22e673789737b4203a68a9c559742846be2747a2a95ed70"
        },
        "64bit": {
            "url": "https://github.com/meshery/meshery/releases/download/v0.6.0-rc.6fe/mesheryctl_0.6.0-rc.6fe_Windows_x86_64.zip",
            "bin": [
                "mesheryctl.exe"
            ],
            "hash": "af4029ac751f2b162d33872d39df07bdf29666749df3dc1d40b0827b1f6925fe"
        }
    },
    "homepage": "https://layer5.io/meshery",
    "license": "Apache 2.0",
    "description": "The Cloud Native Management Plane."
}