{
    "version": "0.8.104",
    "architecture": {
        "32bit": {
            "url": "https://github.com/meshery/meshery/releases/download/v0.8.104/mesheryctl_0.8.104_Windows_i386.zip",
            "bin": [
                "mesheryctl.exe"
            ],
            "hash": "764e5db89a67ec26d3855f8ca6c8aa30b8a1ada7cccba6b0654f194f7cca811e"
        },
        "64bit": {
            "url": "https://github.com/meshery/meshery/releases/download/v0.8.104/mesheryctl_0.8.104_Windows_x86_64.zip",
            "bin": [
                "mesheryctl.exe"
            ],
            "hash": "7b9974571d51ec07ead289a84e96d1a248e985adaa42a15722ac4afb81afb253"
        }
    },
    "homepage": "https://meshery.io",
    "license": "Apache 2.0",
    "description": "The Cloud Native Management Plane."
}