{
    "version": "0.6.0-rc.5s",
    "architecture": {
        "32bit": {
            "url": "https://github.com/meshery/meshery/releases/download/v0.6.0-rc.5s/mesheryctl_0.6.0-rc.5s_Windows_i386.zip",
            "bin": [
                "mesheryctl.exe"
            ],
            "hash": "fc5c1c12a87cbe159e7fc8209358e84e3f05f785648caa6249573c2ea8e1c1c7"
        },
        "64bit": {
            "url": "https://github.com/meshery/meshery/releases/download/v0.6.0-rc.5s/mesheryctl_0.6.0-rc.5s_Windows_x86_64.zip",
            "bin": [
                "mesheryctl.exe"
            ],
            "hash": "45c1faafb74f0d5d1ae8987ef638f51d16b6c5fd50487a78b238952b003af44e"
        }
    },
    "homepage": "https://layer5.io/meshery",
    "license": "Apache 2.0",
    "description": "The Multi-Service Mesh Management Plane."
}