{
    "version": "0.8.154",
    "architecture": {
        "32bit": {
            "url": "https://github.com/meshery/meshery/releases/download/v0.8.154/mesheryctl_0.8.154_Windows_i386.zip",
            "bin": [
                "mesheryctl.exe"
            ],
            "hash": "6f16a04b62b0d97c8c40de753c37270ed1e644d91012bee70cb3d128ea103bd3"
        },
        "64bit": {
            "url": "https://github.com/meshery/meshery/releases/download/v0.8.154/mesheryctl_0.8.154_Windows_x86_64.zip",
            "bin": [
                "mesheryctl.exe"
            ],
            "hash": "5d124748f99c378e82ea117bc9b89ef3c945a3a0bea9ad56e2a23082dbcf31ea"
        }
    },
    "homepage": "https://meshery.io",
    "license": "Apache 2.0",
    "description": "The Cloud Native Management Plane."
}
