{
    "version": "0.8.15",
    "architecture": {
        "32bit": {
            "url": "https://github.com/meshery/meshery/releases/download/v0.8.15/mesheryctl_0.8.15_Windows_i386.zip",
            "bin": [
                "mesheryctl.exe"
            ],
            "hash": "7993bef9510f336599a2fc5f40ea52363b86fe487bceb9ac1dd85ab19d814262"
        },
        "64bit": {
            "url": "https://github.com/meshery/meshery/releases/download/v0.8.15/mesheryctl_0.8.15_Windows_x86_64.zip",
            "bin": [
                "mesheryctl.exe"
            ],
            "hash": "57d12732740b9e7c2155efebe2d4b5bd9ab7d53697d538425285fb250c8c9c74"
        }
    },
    "homepage": "https://meshery.io",
    "license": "Apache 2.0",
    "description": "The Cloud Native Management Plane."
}