{
    "version": "0.7.61",
    "architecture": {
        "32bit": {
            "url": "https://github.com/meshery/meshery/releases/download/v0.7.61/mesheryctl_0.7.61_Windows_i386.zip",
            "bin": [
                "mesheryctl.exe"
            ],
            "hash": "4dd33d4f76ed41ad1150716389f6fb914c018149b571f6f4b39b991b1f919299"
        },
        "64bit": {
            "url": "https://github.com/meshery/meshery/releases/download/v0.7.61/mesheryctl_0.7.61_Windows_x86_64.zip",
            "bin": [
                "mesheryctl.exe"
            ],
            "hash": "b257cea11da0665b3432e6c1183cc85393ffd6583933513bd119211df0f7d1c9"
        }
    },
    "homepage": "https://meshery.io",
    "license": "Apache 2.0",
    "description": "The Cloud Native Management Plane."
}