{
    "version": "0.6.0-rc-5b",
    "architecture": {
        "32bit": {
            "url": "https://github.com/meshery/meshery/releases/download/v0.6.0-rc-5b/mesheryctl_0.6.0-rc-5b_Windows_i386.zip",
            "bin": [
                "mesheryctl.exe"
            ],
            "hash": "76910f2c17ec7840a09923e76157803ec4843804f53f3da8645e069651ed69a6"
        },
        "64bit": {
            "url": "https://github.com/meshery/meshery/releases/download/v0.6.0-rc-5b/mesheryctl_0.6.0-rc-5b_Windows_x86_64.zip",
            "bin": [
                "mesheryctl.exe"
            ],
            "hash": "9b888f8961f7bd1a308f0ffaf0abb79fa4c89601aa23d57c0bbccdc0daf22d32"
        }
    },
    "homepage": "https://layer5.io/meshery",
    "license": "Apache 2.0",
    "description": "The Multi-Service Mesh Management Plane."
}