{
    "version": "0.7.117",
    "architecture": {
        "32bit": {
            "url": "https://github.com/meshery/meshery/releases/download/v0.7.117/mesheryctl_0.7.117_Windows_i386.zip",
            "bin": [
                "mesheryctl.exe"
            ],
            "hash": "3d2132ab2fa925376aa5c5b8fabc15a4dbc183b96ae8fe16b8a3c527417ff281"
        },
        "64bit": {
            "url": "https://github.com/meshery/meshery/releases/download/v0.7.117/mesheryctl_0.7.117_Windows_x86_64.zip",
            "bin": [
                "mesheryctl.exe"
            ],
            "hash": "c8b85cfded0edaad69e44179b50d20412835ea5e12753bc1eaa03ee22f04abe8"
        }
    },
    "homepage": "https://meshery.io",
    "license": "Apache 2.0",
    "description": "The Cloud Native Management Plane."
}